{
  "post_id": "971710682385850",
  "type": "simple_post",
  "post_info": {
    "post_story_id": "UzpfSTEwMDA4NjQwNzgwOTY4Mjo5NzE3MTA2ODIzODU4NTA6OTcxNzEwNjgyMzg1ODUw",
    "media_id": "971710655719186"
  },
  "comments": [
    {
      "text": "https://fly88.uk FLY88 OKVIP CƯỢC WORLD CUP 2026 NHẬN THƯỞNG NGẬP TRÀN",
      "reaction_count": "0",
      "replies": []
    },
    {
      "text": "https://fly88.uk FLY88 OKVIP CƯỢC WORLD CUP 2026 NHẬN THƯỞNG NGẬP TRÀN",
      "reaction_count": "0",
      "replies": []
    },
    {
      "text": "Poster quá đẹp \nRất nhiều chi tiết ẩn ý trong bức ảnh",
      "reaction_count": "0",
      "replies": []
    },
    {
      "text": "",
      "reaction_count": "0",
      "replies": []
    },
    {
      "text": "🔥🔥 CẤT CÁNH THUẬN LỢI - TẶNG 8888K NẠP ĐẦU 🔥🔥\n🍍 https://fly88.uk",
      "reaction_count": "0",
      "replies": []
    },
    {
      "text": "Poster đẹp quá . Tui mê bà Tiểu Vy rồi đó nha",
      "reaction_count": "0",
      "replies": []
    },
    {
      "text": "Càng có tuổi ảnh càng đẹp bây oiii",
      "reaction_count": "0",
      "replies": []
    },
    {
      "text": "Chội a Quốc Trường ck em đúng là hào quang tỏa sáng luôn é 🤣🤣",
      "reaction_count": "0",
      "replies": []
    },
    {
      "text": "Cảnh báo có trai đẹp Yen Phi",
      "reaction_count": "0",
      "replies": []
    },
    {
      "text": "ê nha ê nha Thuc Mien",
      "reaction_count": "0",
      "replies": []
    },
    {
      "text": "thấy hay á Thanh Truc",
      "reaction_count": "0",
      "replies": []
    },
    {
      "text": "Trang Tran có ck của chúng taaa",
      "reaction_count": "0",
      "replies": []
    },
    {
      "text": "Drama tảm tiu hả mng??? V ai là tảm tiêu dạ 🤔",
      "reaction_count": "0",
      "replies": [
        {
          "text": "Hoa Sen  tui đoán bà Anh Phạm nha",
          "reaction_count": "0"
        },
        {
          "text": "Hoa Sen Hình như Tiểu Vy hay sao é",
          "reaction_count": "0"
        }
      ]
    },
    {
      "text": "Cái cầu thang xoắn ốc nhìn y chang con ốc luônnn",
      "reaction_count": "0",
      "replies": []
    },
    {
      "text": "Anh Phạm cười mà làm t xợ á",
      "reaction_count": "0",
      "replies": []
    },
    {
      "text": "C Yên Đan cần được nổi hơn bây giờ 😭😭😭 bả đẹp mà bả giỏi mà còn duyên dáng nựa",
      "reaction_count": "0",
      "replies": []
    },
    {
      "text": "Tiểu Vy với Quốc Trường nhìn hợp quá nè, đẹp đềuuu",
      "reaction_count": "1",
      "replies": []
    },
    {
      "text": "Mong là kịch bản hay thiệt choa em nha, drama um trời lênnn",
      "reaction_count": "0",
      "replies": []
    },
    {
      "text": "phần nhìn là ăn điểm r á, ai cũng đẹp hết trơnn",
      "reaction_count": "0",
      "replies": []
    },
    {
      "text": "á có anh Lương Gia Huy nè, lâu r ms thấy, ổng đẹp kiểu chững chạc gu t nha :))))))",
      "reaction_count": "0",
      "replies": [
        {
          "text": "Nuong Ngoc Anh vẫn hoạt động đều mà c",
          "reaction_count": "0"
        }
      ]
    },
    {
      "text": "Mai Tuyết phim mới nè trà xanh trà ơ đồ đây",
      "reaction_count": "0",
      "replies": []
    },
    {
      "text": "poster 7 người ai cũng đẹp, cụ Chung thì mặc vest đen 🤣",
      "reaction_count": "0",
      "replies": []
    },
    {
      "text": "Có lọt thỏm ông nhạc sĩ nào đâu đây 🤣🤣🤣",
      "reaction_count": "0",
      "replies": []
    },
    {
      "text": "Ko cast nào chịu thua cast nào hả, sao mà đẹp đều v",
      "reaction_count": "0",
      "replies": []
    },
    {
      "text": "poster đẹp dã man v trờiii",
      "reaction_count": "0",
      "replies": []
    },
    {
      "text": "🔥🔥 CẤT CÁNH THUẬN LỢI - TẶNG 8888K NẠP ĐẦU 🔥🔥\n🍍 https://fly88.uk",
      "reaction_count": "0",
      "replies": []
    },
    {
      "text": "cái sự đa năng này đúng là đáng nể đan nha",
      "reaction_count": "0",
      "replies": []
    },
    {
      "text": "thề là tui hóng cái cách đạo diễn xử lý mấy yếu tố tâm linh trongphim á",
      "reaction_count": "0",
      "replies": []
    }
  ]
}